bailamapi/__init__.py
bailamapi/bailam_api.py
bailamapi/json_to_table.py
bailamapi/typestools.py
bailamapi-0.1432.dist-info/LICENSE
bailamapi-0.1432.dist-info/METADATA
bailamapi-0.1432.dist-info/WHEEL
bailamapi-0.1432.dist-info/top_level.txt
bailamapi-0.1432.dist-info/RECORD
