Metadata-Version: 2.1
Name: bailamapi
Version: 0.1432
Summary: Python APi form Bailam:(HEAD
Home-page: UNKNOWN
Author: Olivier Kamoun
Author-email: okamoun@bailam.com
License: Copyright Bailam
Platform: UNKNOWN
Requires-Dist: pandas
Requires-Dist: requests
Requires-Dist: xlrd
Requires-Dist: openpyxl
